register_file.v
module register_file (
    input clk,
    input reg_write,
    input [4:0] rs_addr,
    input [4:0] rt_addr,
    input [4:0] wr_addr,
    input [31:0] wr_data,
    output reg [31:0] rs_data,
    output reg [31:0] rt_data
);
    (* ram_style = "block" *) reg [31:0] bram1 [0:31];
    (* ram_style = "block" *) reg [31:0] bram2 [0:31];

    // BRAM 1: Handles Write (Port A) and Read rs (Port B)
    always @(posedge clk) begin
        if (reg_write && (wr_addr != 5'b0)) begin
            bram1[wr_addr] <= wr_data;
        end
        
        if (reg_write && (wr_addr != 5'b0) && (wr_addr == rs_addr))
            rs_data <= wr_data; // Forwarding
        else
            rs_data <= bram1[rs_addr];
    end

    // BRAM 2: Handles Write (Port A) and Read rt (Port B)
    always @(posedge clk) begin
        if (reg_write && (wr_addr != 5'b0)) begin
            bram2[wr_addr] <= wr_data;
        end
        
        if (reg_write && (wr_addr != 5'b0) && (wr_addr == rt_addr))
            rt_data <= wr_data; // Forwarding
        else
            rt_data <= bram2[rt_addr];
    end
endmodule

main_memory.v
module main_memory(
    input clk,
    input reset,
    
    // Stage 1 - IF
    input [9:0] PC, // PC
    output reg [31:0] instruction, // Instruction fetched
    
    // --- Port B: Data Memory (Stage 4 - MEM) ---
    input write,
    input [9:0] addr, // Address from ALU Result
    input [31:0] data_in,   // Data to store
    output reg [31:0] data_out   // Data loaded (lw)
);
    (* ram_style = "block" *) reg [31:0] memory [0:1023]; // 1024 x 32-bit registers

    initial begin
        $readmemh("instructions.mem", memory);
    end

    // Fetch instruction at PC
    always @(posedge clk) begin
        if (reset) instruction <= 32'b0; // or a NOP-equivalent opcode
        else instruction <= memory[PC];
    end

    // Read/Write (MEM Stage)
    always @(posedge clk) begin
        if (write) memory[addr] <= data_in;
        data_out <= memory[addr];
    end
endmodule

processor.v
module MIPS32 # (
    // R-type instructions
    parameter [5:0] ADD = 6'b000001, SUB = 6'b000010, AND = 6'b000011, OR = 6'b000100,
    parameter [5:0] SLT = 6'b000101, MUL = 6'b000110, HLT = 6'b111111,

    // I-type instructions
    parameter [5:0] LW = 6'b001000, SW = 6'b001001,
    parameter [5:0] ADDI = 6'b001010, SUBI = 6'b001011, SLTI = 6'b001100,
    parameter [5:0] BNEQZ = 6'b001101, BEQZ = 6'b001110,

    // J-type instructions
    parameter [5:0] J = 6'b010000,

    // NOP instruction
    parameter [5:0] NOP_INSTRUCTION = 6'b000000,

    // Instruction types
    parameter [2:0] R = 3'b000, I = 3'b001, LOAD = 3'b010, STORE = 3'b011, 
    parameter [2:0] BRANCH = 3'b100, JUMP = 3'b101, NOP = 3'b110, HALT = 3'b111
) (
    input clk,
    input reset,

    output [9:0] dbg_pc,
    output dbg_halted,
    output [31:0] dbg_alu_out,
    output [31:0] dbg_instr
);
    (* mark_debug = "true" *) reg [9:0] PC;
    reg [31:0] IF_ID_NPC;
    (* mark_debug = "true" *) wire [31:0] IF_ID_IR;
    
    (* mark_debug = "true" *) reg [31:0] ID_EX_NPC, ID_EX_IR, ID_EX_IMM;
    wire [31:0] ID_EX_A, ID_EX_B;

    (* mark_debug = "true" *) reg [31:0] EX_MEM_IR, EX_MEM_ALU_OUT, EX_MEM_B;
    reg EX_MEM_WRITE;
    
    (* mark_debug = "true" *) reg [31:0] MEM_WB_IR, MEM_WB_ALU_OUT;
    wire [31:0] MEM_WB_LMD;

    reg [2:0] ID_EX_TYPE, EX_MEM_TYPE, MEM_WB_TYPE;
    (* mark_debug = "true" *) reg HALTED, TAKEN_BRANCH;

    
    wire [9:0] INST_ADDR;
    assign INST_ADDR = (TAKEN_BRANCH ||  (EX_MEM_TYPE == JUMP)) ? EX_MEM_ALU_OUT[9:0] : PC;

    assign dbg_pc = PC;
    assign dbg_halted = HALTED;
    assign dbg_alu_out = EX_MEM_ALU_OUT;
    assign dbg_instr = MEM_WB_IR;

    main_memory memory (
        .clk(clk),
        .reset(reset),
        .PC(INST_ADDR),
        .instruction(IF_ID_IR),
        .write(EX_MEM_WRITE),
        .addr(EX_MEM_ALU_OUT[9:0]),
        .data_in(EX_MEM_B),
        .data_out(MEM_WB_LMD)
    );

    wire reg_write;
    assign reg_write = !reset && !HALTED && 
    ((MEM_WB_TYPE == R) || (MEM_WB_TYPE == I) || (MEM_WB_TYPE == LOAD));

    // Target register: rd for R-type, rt for I-type and LOADs
    wire [4:0] wr_addr;
    assign wr_addr = (MEM_WB_TYPE == R) ? MEM_WB_IR[15:11] : MEM_WB_IR[20:16];

    // Data source: LMD for LOADs, ALU output for R-type / I-type
    wire [31:0] wr_data;
    assign wr_data = (MEM_WB_TYPE == LOAD) ? MEM_WB_LMD : MEM_WB_ALU_OUT;

    register_file registers (
        .clk(clk),
        .reg_write(reg_write),
        .rs_addr(IF_ID_IR[25:21]),
        .rs_data(ID_EX_A),
        .rt_addr(IF_ID_IR[20:16]),
        .rt_data(ID_EX_B),
        .wr_addr(wr_addr),
        .wr_data(wr_data)
    );


    // Stage 1: Instruction Fetch (IF)
    always @(posedge clk) begin
        if (reset) begin
            PC <= 10'd0;
            IF_ID_NPC <= 32'd0;
        end else if (!HALTED) begin
            if (TAKEN_BRANCH ||  (EX_MEM_TYPE == JUMP)) begin
                IF_ID_NPC <= EX_MEM_ALU_OUT + 1;
                PC <= EX_MEM_ALU_OUT[9:0] + 1;
            end else begin
                IF_ID_NPC <= PC + 1;
                PC <= PC + 1;
            end
        end
    end

    // Stage 2: Instruction Decode (ID)
    always @(posedge clk) begin
        if (reset) begin
            ID_EX_IR <= 0;
            ID_EX_NPC <= 0;
            ID_EX_IMM <= 0;
            ID_EX_TYPE <= NOP;
        end else if (!HALTED) begin
            ID_EX_IR <= IF_ID_IR;
            ID_EX_NPC <= IF_ID_NPC;

            ID_EX_IMM <= {{16{IF_ID_IR[15]}}, IF_ID_IR[15:0]};

            if (TAKEN_BRANCH) ID_EX_TYPE <= NOP;
            else begin
                case (IF_ID_IR[31:26])
                    NOP_INSTRUCTION : ID_EX_TYPE <= NOP;
                    ADD, SUB, AND, OR, SLT, MUL : ID_EX_TYPE <= R;
                    ADDI, SUBI, SLTI : ID_EX_TYPE <= I;
                    LW : ID_EX_TYPE <= LOAD;
                    SW : ID_EX_TYPE <= STORE;
                    BEQZ, BNEQZ : ID_EX_TYPE <= BRANCH;
                    J : ID_EX_TYPE <= JUMP;
                    HLT : ID_EX_TYPE <= HALT;
                    default : ID_EX_TYPE <= HALT;
                endcase
            end
        end
    end

    // Stage 3: Execute (EX)
    always @(posedge clk) begin
        if (reset) begin
            EX_MEM_TYPE <= NOP;
            EX_MEM_IR <= 0;
            EX_MEM_ALU_OUT <= 0;
            EX_MEM_B <= 0;
            EX_MEM_WRITE <= 1'b0;
            TAKEN_BRANCH <= 0;
        end else if (!HALTED) begin
            EX_MEM_IR <= ID_EX_IR;
            EX_MEM_B <= ID_EX_B;
            TAKEN_BRANCH <= 0;

            if (TAKEN_BRANCH) begin
                // Instruction B is in EX right now! Kill it by converting to NOP.
                EX_MEM_TYPE <= NOP;
                EX_MEM_WRITE <= 1'b0;
                EX_MEM_IR <= 0;
                EX_MEM_ALU_OUT <= 0;
            end else begin
                EX_MEM_TYPE <= ID_EX_TYPE;
                EX_MEM_WRITE <= (ID_EX_TYPE == STORE);
                case (ID_EX_TYPE)
                    R : begin
                        case (ID_EX_IR[31:26])
                            ADD : EX_MEM_ALU_OUT <= ID_EX_A + ID_EX_B;
                            SUB : EX_MEM_ALU_OUT <= ID_EX_A - ID_EX_B;
                            AND : EX_MEM_ALU_OUT <= ID_EX_A & ID_EX_B;
                            OR  : EX_MEM_ALU_OUT <= ID_EX_A | ID_EX_B;
                            SLT : EX_MEM_ALU_OUT <= {31'b0, $signed(ID_EX_A) < $signed(ID_EX_B)};
                            MUL : EX_MEM_ALU_OUT <= ID_EX_A * ID_EX_B;
                            default : EX_MEM_ALU_OUT <= 32'h00000000;
                        endcase
                    end

                    I : begin
                        case (ID_EX_IR[31:26])
                            ADDI : EX_MEM_ALU_OUT <= ID_EX_A + ID_EX_IMM;
                            SUBI : EX_MEM_ALU_OUT <= ID_EX_A - ID_EX_IMM;
                            SLTI : EX_MEM_ALU_OUT <= {31'b0, $signed(ID_EX_A) < $signed(ID_EX_IMM)};
                            default: EX_MEM_ALU_OUT <= 32'h00000000;
                        endcase
                    end

                    LOAD, STORE : begin
                        EX_MEM_ALU_OUT <= ID_EX_A + ID_EX_IMM;
                    end

                    BRANCH : begin
                        EX_MEM_ALU_OUT <= ID_EX_NPC + ID_EX_IMM;
                        TAKEN_BRANCH <= (~ID_EX_IR[26] && (~|ID_EX_A)) || (ID_EX_IR[26] && (|ID_EX_A));
                    end

                    JUMP : begin
                        EX_MEM_ALU_OUT <= ID_EX_NPC + ID_EX_IMM;
                        TAKEN_BRANCH <= 1'b1;
                    end

                    default : EX_MEM_ALU_OUT <= 32'h00000000;
                endcase
            end
        end
    end

    // Stage 4: Memory Access (Mem)
    always @(posedge clk) begin
        // MEM_WB_LMD
        if (reset) begin
            MEM_WB_IR <= 0;
            MEM_WB_TYPE <= NOP;
            MEM_WB_ALU_OUT <= 0;
        end else if (!HALTED) begin
            MEM_WB_IR <= EX_MEM_IR;
            MEM_WB_TYPE <= EX_MEM_TYPE;
            MEM_WB_ALU_OUT <= EX_MEM_ALU_OUT;
            // memory handles reading to MEM_WB_LMD and writing EX_MEM_B to memory in case of a store instruction
        end
    end

    // Stage 5: Write back (WB)
    always @(posedge clk) begin
        if (reset) HALTED <= 1'b0;
        else if (MEM_WB_TYPE == HALT) HALTED <= 1'b1;
    end
endmodule

testbenches/testbench1.v
module testbench1;
    initial begin
        $dumpfile("simulation/mips_test1.vcd");
        $dumpvars(0, testbench1);
        #600 $finish;
    end

    reg clk = 0;
    always #5 clk = ~clk;

    reg reset;
    initial begin
        reset = 1'b1;
        #7 reset = 1'b0;
    end

    MIPS32 processor (
        .clk(clk),
        .reset(reset)
    );

    integer k;

    initial begin
        $readmemh("testbenches/instructions/instructions1.mem", processor.memory.memory);
        
        for (k = 0; k < 32; k = k + 1) begin
            processor.registers.bram1[k] = k;
            processor.registers.bram2[k] = k;
        end

        #280;
        for (k = 0; k < 6; k = k + 1) begin
            $display("R%0d = %0d", k, processor.registers.bram1[k]);
        end
        check();
    end

    task check();
        reg [31:0] r1_add_r2, sum;
        begin
            r1_add_r2 = processor.registers.bram1[1] + processor.registers.bram1[2];
            sum = processor.registers.bram1[1] + processor.registers.bram1[2] + processor.registers.bram1[3];

            if (processor.registers.bram1[4] != r1_add_r2) begin
                $display("FAILED : Error computing R1 + R2 | Expected : %0d | Got : %0d",
                    r1_add_r2, processor.registers.bram1[4]);
            end else if (processor.registers.bram1[5] != sum) begin
                $display("FAILED : Error computing final sum | Expected : %0d | Got : %0d",
                    sum, processor.registers.bram1[5]);
            end else begin
                $display("PASSED : Computed correct sum | Expected : %0d | Got : %0d",
                    sum, processor.registers.bram1[5]);
            end
        end
    endtask
endmodule

simulation/mips_test1.vcd
$date
	Mon Aug  3 15:29:08 2026
$end
$version
	Icarus Verilog
$end
$timescale
	1s
$end
$scope module testbench1 $end
$var reg 1 ! clk $end
$var reg 1 " reset $end
$var integer 32 # k [31:0] $end
$scope module processor $end
$var wire 1 ! clk $end
$var wire 32 $ dbg_alu_out [31:0] $end
$var wire 1 % dbg_halted $end
$var wire 32 & dbg_instr [31:0] $end
$var wire 10 ' dbg_pc [9:0] $end
$var wire 1 ( reg_write $end
$var wire 1 " reset $end
$var wire 32 ) wr_data [31:0] $end
$var wire 5 * wr_addr [4:0] $end
$var wire 32 + MEM_WB_LMD [31:0] $end
$var wire 10 , INST_ADDR [9:0] $end
$var wire 32 - IF_ID_IR [31:0] $end
$var wire 32 . ID_EX_B [31:0] $end
$var wire 32 / ID_EX_A [31:0] $end
$var parameter 6 0 ADD $end
$var parameter 6 1 ADDI $end
$var parameter 6 2 AND $end
$var parameter 6 3 BEQZ $end
$var parameter 6 4 BNEQZ $end
$var parameter 3 5 BRANCH $end
$var parameter 3 6 HALT $end
$var parameter 6 7 HLT $end
$var parameter 3 8 I $end
$var parameter 6 9 J $end
$var parameter 3 : JUMP $end
$var parameter 3 ; LOAD $end
$var parameter 6 < LW $end
$var parameter 6 = MUL $end
$var parameter 3 > NOP $end
$var parameter 6 ? NOP_INSTRUCTION $end
$var parameter 6 @ OR $end
$var parameter 3 A R $end
$var parameter 6 B SLT $end
$var parameter 6 C SLTI $end
$var parameter 3 D STORE $end
$var parameter 6 E SUB $end
$var parameter 6 F SUBI $end
$var parameter 6 G SW $end
$var reg 32 H EX_MEM_ALU_OUT [31:0] $end
$var reg 32 I EX_MEM_B [31:0] $end
$var reg 32 J EX_MEM_IR [31:0] $end
$var reg 3 K EX_MEM_TYPE [2:0] $end
$var reg 1 L EX_MEM_WRITE $end
$var reg 1 M HALTED $end
$var reg 32 N ID_EX_IMM [31:0] $end
$var reg 32 O ID_EX_IR [31:0] $end
$var reg 32 P ID_EX_NPC [31:0] $end
$var reg 3 Q ID_EX_TYPE [2:0] $end
$var reg 32 R IF_ID_NPC [31:0] $end
$var reg 32 S MEM_WB_ALU_OUT [31:0] $end
$var reg 32 T MEM_WB_IR [31:0] $end
$var reg 3 U MEM_WB_TYPE [2:0] $end
$var reg 10 V PC [9:0] $end
$var reg 1 W TAKEN_BRANCH $end
$scope module memory $end
$var wire 10 X PC [9:0] $end
$var wire 10 Y addr [9:0] $end
$var wire 1 ! clk $end
$var wire 32 Z data_in [31:0] $end
$var wire 1 " reset $end
$var wire 1 L write $end
$var reg 32 [ data_out [31:0] $end
$var reg 32 \ instruction [31:0] $end
$upscope $end
$scope module registers $end
$var wire 1 ! clk $end
$var wire 1 ( reg_write $end
$var wire 5 ] rs_addr [4:0] $end
$var wire 5 ^ rt_addr [4:0] $end
$var wire 5 _ wr_addr [4:0] $end
$var wire 32 ` wr_data [31:0] $end
$var reg 32 a rs_data [31:0] $end
$var reg 32 b rt_data [31:0] $end
$upscope $end
$upscope $end
$scope task check $end
$var reg 32 c r1_add_r2 [31:0] $end
$var reg 32 d sum [31:0] $end
$upscope $end
$upscope $end
$enddefinitions $end
$comment Show the parameter values. $end
$dumpall
b1001 G
b1011 F
b10 E
b11 D
b1100 C
b101 B
b0 A
b100 @
b0 ?
b110 >
b110 =
b1000 <
b10 ;
b101 :
b10000 9
b1 8
b111111 7
b111 6
b100 5
b1101 4
b1110 3
b11 2
b1010 1
b1 0
$end
#0
$dumpvars
bx d
bx c
bx b
bx a
bx `
bx _
bx ^
bx ]
bx \
bx [
bx Z
bx Y
bx X
xW
bx V
bx U
bx T
bx S
bx R
bx Q
bx P
bx O
bx N
xM
xL
bx K
bx J
bx I
bx H
bx /
bx .
bx -
bx ,
bx +
bx *
bx )
0(
bx '
bx &
x%
bx $
b100000 #
1"
0!
$end
#5
b0 ^
b0 ]
b0 ,
b0 X
b0 Y
b0 *
b0 _
b0 )
b0 `
b0 -
b0 \
b0 R
b0 '
b0 V
b110 Q
b0 N
b0 P
b0 O
0W
0L
b0 I
b0 Z
b0 $
b0 H
b0 J
b110 K
b0 S
b110 U
b0 &
b0 T
0%
0M
1!
#7
0"
#10
0!
#15
b1 ,
b1 X
b1 ^
bx I
bx Z
b1 '
b1 V
b1 R
b0 .
b0 b
b0 /
b0 a
b101000000000010000000000001010 +
b101000000000010000000000001010 [
b101000000000010000000000001010 -
b101000000000010000000000001010 \
1!
#20
0!
#25
b10 ^
b10 ,
b10 X
b101000000000100000000000010100 -
b101000000000100000000000010100 \
b1 .
b1 b
b10 '
b10 V
b10 R
b1 Q
b1010 N
b1 P
b101000000000010000000000001010 O
b0 I
b0 Z
1!
#30
0!
#35
b1010 Y
b11 ,
b11 X
b11 ^
b1010 $
b1010 H
b1 K
b1 I
b1 Z
b101000000000010000000000001010 J
b10100 N
b10 P
b101000000000100000000000010100 O
b11 '
b11 V
b11 R
b10 .
b10 b
b101000000000110000000000011001 -
b101000000000110000000000011001 \
1!
#40
0!
#45
1(
b1 *
b1 _
b1 ^
b100 ,
b100 X
b10100 Y
b1010 )
b1010 `
b101000000000010000000000001010 -
b101000000000010000000000001010 \
bx +
bx [
b11 .
b11 b
b100 '
b100 V
b100 R
b11001 N
b11 P
b101000000000110000000000011001 O
b10100 $
b10100 H
b10 I
b10 Z
b101000000000100000000000010100 J
b1010 S
b1 U
b101000000000010000000000001010 &
b101000000000010000000000001010 T
1!
#50
0!
#55
b10 *
b10 _
b10100 )
b10100 `
b11001 Y
b101 ,
b101 X
b10 ^
b1 ]
b10100 S
b101000000000100000000000010100 &
b101000000000100000000000010100 T
b11001 $
b11001 H
b11 I
b11 Z
b101000000000110000000000011001 J
b1010 N
b100 P
b101000000000010000000000001010 O
b101 '
b101 V
b101 R
b1010 .
b1010 b
b100001000100010000000000000 -
b100001000100010000000000000 \
1!
#60
0!
#65
b11 *
b11 _
b110 ^
b110 ]
b110 ,
b110 X
b1010 Y
b11001 )
b11001 `
b10000110001100011000000000000 -
b10000110001100011000000000000 \
b1010 /
b1010 a
b10100 .
b10100 b
b110 '
b110 V
b110 R
b0 Q
b10000000000000 N
b101 P
b100001000100010000000000000 O
b1010 $
b1010 H
b1010 I
b1010 Z
b101000000000010000000000001010 J
b11001 S
b101000000000110000000000011001 &
b101000000000110000000000011001 T
1!
#70
0!
#75
b1 *
b1 _
b1010 )
b1010 `
b11110 Y
b111 ,
b111 X
b1010 S
b101000000000010000000000001010 &
b101000000000010000000000001010 T
b11110 $
b11110 H
b0 K
b10100 I
b10100 Z
b100001000100010000000000000 J
b11000000000000 N
b110 P
b10000110001100011000000000000 O
b111 '
b111 V
b111 R
b110 .
b110 b
b110 /
b110 a
1!
#80
0!
#85
b11 ^
b100 ]
b1000 ,
b1000 X
b110 Y
b11110 )
b11110 `
b100 *
b100 _
b100100000110010100000000000 -
b100100000110010100000000000 \
b1000 '
b1000 V
b1000 R
b111 P
b110 $
b110 H
b110 I
b110 Z
b10000110001100011000000000000 J
b11110 S
b0 U
b100001000100010000000000000 &
b100001000100010000000000000 T
1!
#90
0!
#95
b110 *
b110 _
b110 )
b110 `
b1001 ,
b1001 X
b0 ^
b0 ]
b110 S
b10000110001100011000000000000 &
b10000110001100011000000000000 T
b10100000000000 N
b1000 P
b100100000110010100000000000 O
b1001 '
b1001 V
b1001 R
b11001 .
b11001 b
b11110 /
b11110 a
b10000110001100011000000000000 +
b10000110001100011000000000000 [
b11111100000000000000000000000000 -
b11111100000000000000000000000000 \
1!
#100
0!
#105
bx ^
bx ]
b1010 ,
b1010 X
b110111 Y
bx -
bx \
b0 /
b0 a
b0 .
b0 b
b1010 '
b1010 V
b1010 R
b111 Q
b0 N
b1001 P
b11111100000000000000000000000000 O
b110111 $
b110111 H
b11001 I
b11001 Z
b100100000110010100000000000 J
1!
#110
0!
#115
b101 *
b101 _
b110111 )
b110111 `
b0 Y
b1011 ,
b1011 X
b110111 S
b100100000110010100000000000 &
b100100000110010100000000000 T
b0 $
b0 H
b111 K
b0 I
b0 Z
b11111100000000000000000000000000 J
bx N
b1010 P
bx O
b1011 '
b1011 V
b1011 R
bx .
bx b
bx /
bx a
bx +
bx [
1!
#120
0!
#125
0(
b1100 ,
b1100 X
b0 )
b0 `
b0 *
b0 _
b101000000000010000000000001010 +
b101000000000010000000000001010 [
b1100 '
b1100 V
b1100 R
b1011 P
bx I
bx Z
bx J
b0 S
b111 U
b11111100000000000000000000000000 &
b11111100000000000000000000000000 T
1!
#130
0!
#135
bx *
bx _
b1101 ,
b1101 X
1%
1M
bx &
bx T
b1100 P
b1101 '
b1101 V
b1101 R
1!
#140
0!
#145
1!
#150
0!
#155
1!
#160
0!
#165
1!
#170
0!
#175
1!
#180
0!
#185
1!
#190
0!
#195
1!
#200
0!
#205
1!
#210
0!
#215
1!
#220
0!
#225
1!
#230
0!
#235
1!
#240
0!
#245
1!
#250
0!
#255
1!
#260
0!
#265
1!
#270
0!
#275
1!
#280
0!
b110111 d
b11110 c
b110 #
